mmpackage/__init__.py
mmpackage/file.py
mmpackage-0.0.2.dist-info/METADATA
mmpackage-0.0.2.dist-info/WHEEL
mmpackage-0.0.2.dist-info/top_level.txt
mmpackage-0.0.2.dist-info/RECORD
